aliyunsdkalimt/__init__.py
aliyunsdkalimt/endpoint.py
aliyunsdkalimt/request/__init__.py
aliyunsdkalimt/request/v20181012/CreateDocTranslateTaskRequest.py
aliyunsdkalimt/request/v20181012/CreateImageTranslateTaskRequest.py
aliyunsdkalimt/request/v20181012/GetBatchTranslateRequest.py
aliyunsdkalimt/request/v20181012/GetDetectLanguageRequest.py
aliyunsdkalimt/request/v20181012/GetDocTranslateTaskRequest.py
aliyunsdkalimt/request/v20181012/GetImageDiagnoseRequest.py
aliyunsdkalimt/request/v20181012/GetImageTranslateRequest.py
aliyunsdkalimt/request/v20181012/GetImageTranslateTaskRequest.py
aliyunsdkalimt/request/v20181012/GetTitleDiagnoseRequest.py
aliyunsdkalimt/request/v20181012/GetTitleGenerateRequest.py
aliyunsdkalimt/request/v20181012/GetTitleIntelligenceRequest.py
aliyunsdkalimt/request/v20181012/GetTranslateImageBatchResultRequest.py
aliyunsdkalimt/request/v20181012/GetTranslateReportRequest.py
aliyunsdkalimt/request/v20181012/OpenAlimtServiceRequest.py
aliyunsdkalimt/request/v20181012/TranslateCertificateRequest.py
aliyunsdkalimt/request/v20181012/TranslateECommerceRequest.py
aliyunsdkalimt/request/v20181012/TranslateGeneralRequest.py
aliyunsdkalimt/request/v20181012/TranslateImageBatchRequest.py
aliyunsdkalimt/request/v20181012/TranslateImageRequest.py
aliyunsdkalimt/request/v20181012/TranslateRequest.py
aliyunsdkalimt/request/v20181012/__init__.py
aliyun_python_sdk_alimt-3.2.0.dist-info/LICENSE
aliyun_python_sdk_alimt-3.2.0.dist-info/METADATA
aliyun_python_sdk_alimt-3.2.0.dist-info/WHEEL
aliyun_python_sdk_alimt-3.2.0.dist-info/top_level.txt
aliyun_python_sdk_alimt-3.2.0.dist-info/RECORD
